ring_counter_folder/ring_counter.v
module dff(
  input d,clk,rst,initialize_output,
  output reg q,qbar
);

always @(posedge clk or posedge rst)
begin 
 if(rst) 
 begin
  q<=1'b0;
  qbar<=1'b1;
 end
else if (initialize_output) begin 
 q<=1'b1;
 qbar<=1'b0;
end
else begin
q<=d;
qbar<=~d;
end
end
endmodule

// main logic
module ring_counter(

input clk,rst,initialize_output,
output wire [3:0] qout,qbar
);



// wire [3:0] qout;

// assign qout[0]=qout[3];
// assign qout[1]=qout[2];
// assign qout[2]=qout[1];
// assign qout[3]=qout[0];

dff d0 (qbar[3],clk,rst,initialize_output,qout[0],qbar[0]);                 // dff(d,clk,rst,initialize_output,q,qbar)
dff d1 (qout[0],clk,rst,1'b0,qout[1],qbar[1]);
dff d2 (qout[1],clk,rst,1'b0,qout[2],qbar[2]);                            // dff d0 (qout[3]) = Ring_counter 
dff d3 (qout[2],clk,rst,1'b0,qout[3],qbar[3]);                            //  dff d0 (qbar[3]) = Jhonson_counter                      




endmodule

ring_counter_folder/ring_counter_tb.v
`timescale 1ns/1ns
`include "ring_counter.v"




module ring_counter_tb;

reg clk,rst,initialize_output;
wire [3:0] qout,qbar;


ring_counter dut (.clk(clk),.rst(rst),.initialize_output(initialize_output),.qout(qout),.qbar(qbar));




initial begin 
clk=1;
rst=0;
initialize_output=0;
end

always #5 clk=~clk;

initial begin 
$display("TIME \t QOUT");
$monitor("%g ns\t %b",$time,qout);

rst=1'b1;                       // reset to get zero
#10;
rst=1'b0;

#10;
initialize_output=1'b1;
#10;                                 // Initialize a flip flop output to 1
initialize_output=1'b0;

#100;                                   // run for 100 ns 

rst=1'b1;              // again reset
#10;
rst=1'b0;

#100; $finish;

end

initial 
begin
$dumpfile("ring_counter_sim.vcd");
$dumpvars(0,ring_counter_tb);
end



endmodule

ring_counter_folder/ring_counter_sim.vcd
$date
	Mon Jul 07 18:04:38 2025
$end
$version
	Icarus Verilog
$end
$timescale
	1ns
$end
$scope module ring_counter_tb $end
$var wire 4 ! qout [3:0] $end
$var wire 4 " qbar [3:0] $end
$var reg 1 # clk $end
$var reg 1 $ initialize_output $end
$var reg 1 % rst $end
$scope module dut $end
$var wire 1 # clk $end
$var wire 1 $ initialize_output $end
$var wire 1 % rst $end
$var wire 4 & qout [3:0] $end
$var wire 4 ' qbar [3:0] $end
$scope module d0 $end
$var wire 1 # clk $end
$var wire 1 ( d $end
$var wire 1 $ initialize_output $end
$var wire 1 % rst $end
$var reg 1 ) q $end
$var reg 1 * qbar $end
$upscope $end
$scope module d1 $end
$var wire 1 # clk $end
$var wire 1 + d $end
$var wire 1 , initialize_output $end
$var wire 1 % rst $end
$var reg 1 - q $end
$var reg 1 . qbar $end
$upscope $end
$scope module d2 $end
$var wire 1 # clk $end
$var wire 1 / d $end
$var wire 1 0 initialize_output $end
$var wire 1 % rst $end
$var reg 1 1 q $end
$var reg 1 2 qbar $end
$upscope $end
$scope module d3 $end
$var wire 1 # clk $end
$var wire 1 3 d $end
$var wire 1 4 initialize_output $end
$var wire 1 % rst $end
$var reg 1 5 q $end
$var reg 1 6 qbar $end
$upscope $end
$upscope $end
$upscope $end
$enddefinitions $end
$comment Show the parameter values. $end
$dumpall
$end
#0
$dumpvars
16
05
04
03
12
01
00
0/
1.
0-
0,
0+
1*
0)
0(
b1111 '
b0 &
1%
0$
1#
b1111 "
b0 !
$end
#5
0#
#10
1#
0%
#15
0#
#20
1+
b1110 "
b1110 '
0*
b1 !
b1 &
1)
1#
1$
#25
0#
#30
1/
0+
0.
1-
b1101 "
b1101 '
1*
b10 !
b10 &
0)
1#
0$
#35
0#
#40
0/
13
1.
0-
b1011 "
b1011 '
02
b100 !
b100 &
11
1#
#45
0#
#50
1(
03
06
15
b111 "
b111 '
12
b1000 !
b1000 &
01
1#
#55
0#
#60
1+
0(
0*
1)
b1110 "
b1110 '
16
b1 !
b1 &
05
1#
#65
0#
#70
1/
0+
0.
1-
b1101 "
b1101 '
1*
b10 !
b10 &
0)
1#
#75
0#
#80
0/
13
1.
0-
b1011 "
b1011 '
02
b100 !
b100 &
11
1#
#85
0#
#90
1(
03
06
15
b111 "
b111 '
12
b1000 !
b1000 &
01
1#
#95
0#
#100
1+
0(
0*
1)
b1110 "
b1110 '
16
b1 !
b1 &
05
1#
#105
0#
#110
1/
0+
0.
1-
b1101 "
b1101 '
1*
b10 !
b10 &
0)
1#
#115
0#
#120
0/
13
1.
0-
b1011 "
b1011 '
02
b100 !
b100 &
11
1#
#125
0#
#130
03
b1111 "
b1111 '
12
b0 !
b0 &
01
1#
1%
#135
0#
#140
1#
0%
