4bit_asynch_upcounter/up_asynch.v
`timescale 1ns/1ns


module tff (
input clk,rst,t_in,
output reg q,qbar

);

always @(posedge clk or posedge rst ) begin

if(rst)begin
    q<=1'b0;
    qbar<=1'b1;
end
else begin
    if(t_in) begin 
        q<=~q;
        qbar<=q;
    end
    else begin 
        q<=q;
        qbar<=qbar;
    end
end
    
end

endmodule


module up_asynch(
input clk,rst,t_in,
output [3:0] q,qbar

);

// up counting         // for Down counting just replace .clk(qbar[]) -->.clk(q[])


// tff t1 (.clk(clk), .rst(rst), .t_in(t_in), .q(q[0]), .qbar(qbar[0]));
// tff t2 (.clk(qbar[0]), .rst(rst), .t_in(t_in), .q(q[1]), .qbar(qbar[1]));  
// tff t3 (.clk(qbar[1]), .rst(rst), .t_in(t_in), .q(q[2]), .qbar(qbar[2]));
// tff t4 (.clk(qbar[2]), .rst(rst), .t_in(t_in), .q(q[3]), .qbar(qbar[3]));


//Down counting

tff t1 (.clk(clk), .rst(rst), .t_in(t_in), .q(q[0]), .qbar(qbar[0]));
tff t2 (.clk(q[0]), .rst(rst), .t_in(t_in), .q(q[1]), .qbar(qbar[1]));  
tff t3 (.clk(q[1]), .rst(rst), .t_in(t_in), .q(q[2]), .qbar(qbar[2]));
tff t4 (.clk(q[2]), .rst(rst), .t_in(t_in), .q(q[3]), .qbar(qbar[3]));





endmodule


////////////////////////////// TESTBENCH ////////////////////////////////////////

module up_asynch_tb;

reg clk,rst,t_in;
wire [3:0] q,qbar;


up_asynch dut (
    .clk(clk),
    .rst(rst),
    .t_in(t_in),
    .q(q),
    .qbar(qbar)
);

always #5 clk=~clk;



initial begin 
$display("TIME\tQ:");
$monitor("%gns\tQ:%d",$time,q);
end

initial begin
clk=1'b1;
t_in=1'b1;
rst=1'b1;
#10;
rst=1'b0;
#320;$finish;
end

initial begin
$dumpfile("up_asynch_sim.vcd");
$dumpvars(0,up_asynch_tb);
end
endmodule

4bit_asynch_upcounter/up_asynch_sim.vcd
$date
	Thu Jul 17 10:37:42 2025
$end
$version
	Icarus Verilog
$end
$timescale
	1ns
$end
$scope module up_asynch_tb $end
$var wire 4 ! qbar [3:0] $end
$var wire 4 " q [3:0] $end
$var reg 1 # clk $end
$var reg 1 $ rst $end
$var reg 1 % t_in $end
$scope module dut $end
$var wire 1 # clk $end
$var wire 1 $ rst $end
$var wire 1 % t_in $end
$var wire 4 & qbar [3:0] $end
$var wire 4 ' q [3:0] $end
$scope module t1 $end
$var wire 1 # clk $end
$var wire 1 $ rst $end
$var wire 1 % t_in $end
$var reg 1 ( q $end
$var reg 1 ) qbar $end
$upscope $end
$scope module t2 $end
$var wire 1 * clk $end
$var wire 1 $ rst $end
$var wire 1 % t_in $end
$var reg 1 + q $end
$var reg 1 , qbar $end
$upscope $end
$scope module t3 $end
$var wire 1 - clk $end
$var wire 1 $ rst $end
$var wire 1 % t_in $end
$var reg 1 . q $end
$var reg 1 / qbar $end
$upscope $end
$scope module t4 $end
$var wire 1 0 clk $end
$var wire 1 $ rst $end
$var wire 1 % t_in $end
$var reg 1 1 q $end
$var reg 1 2 qbar $end
$upscope $end
$upscope $end
$upscope $end
$enddefinitions $end
$comment Show the parameter values. $end
$dumpall
$end
#0
$dumpvars
12
01
00
1/
0.
0-
1,
0+
0*
1)
0(
b0 '
b1111 &
1%
1$
1#
b0 "
b1111 !
$end
#5
0#
#10
02
11
10
0/
1.
1-
0,
1+
1*
b0 !
b0 &
0)
b1111 "
b1111 '
1(
1#
0$
#15
0#
#20
0*
b1 !
b1 &
1)
b1110 "
b1110 '
0(
1#
#25
0#
#30
0-
1,
0+
1*
b10 !
b10 &
0)
b1101 "
b1101 '
1(
1#
#35
0#
#40
0*
b11 !
b11 &
1)
b1100 "
b1100 '
0(
1#
#45
0#
#50
00
1/
0.
1-
0,
1+
1*
b100 !
b100 &
0)
b1011 "
b1011 '
1(
1#
#55
0#
#60
0*
b101 !
b101 &
1)
b1010 "
b1010 '
0(
1#
#65
0#
#70
0-
1,
0+
1*
b110 !
b110 &
0)
b1001 "
b1001 '
1(
1#
#75
0#
#80
0*
b111 !
b111 &
1)
b1000 "
b1000 '
0(
1#
#85
0#
#90
12
01
10
0/
1.
1-
0,
1+
1*
b1000 !
b1000 &
0)
b111 "
b111 '
1(
1#
#95
0#
#100
0*
b1001 !
b1001 &
1)
b110 "
b110 '
0(
1#
#105
0#
#110
0-
1,
0+
1*
b1010 !
b1010 &
0)
b101 "
b101 '
1(
1#
#115
0#
#120
0*
b1011 !
b1011 &
1)
b100 "
b100 '
0(
1#
#125
0#
#130
00
1/
0.
1-
0,
1+
1*
b1100 !
b1100 &
0)
b11 "
b11 '
1(
1#
#135
0#
#140
0*
b1101 !
b1101 &
1)
b10 "
b10 '
0(
1#
#145
0#
#150
0-
1,
0+
1*
b1110 !
b1110 &
0)
b1 "
b1 '
1(
1#
#155
0#
#160
0*
b1111 !
b1111 &
1)
b0 "
b0 '
0(
1#
#165
0#
#170
02
11
10
0/
1.
1-
0,
1+
1*
b0 !
b0 &
0)
b1111 "
b1111 '
1(
1#
#175
0#
#180
0*
b1 !
b1 &
1)
b1110 "
b1110 '
0(
1#
#185
0#
#190
0-
1,
0+
1*
b10 !
b10 &
0)
b1101 "
b1101 '
1(
1#
#195
0#
#200
0*
b11 !
b11 &
1)
b1100 "
b1100 '
0(
1#
#205
0#
#210
00
1/
0.
1-
0,
1+
1*
b100 !
b100 &
0)
b1011 "
b1011 '
1(
1#
#215
0#
#220
0*
b101 !
b101 &
1)
b1010 "
b1010 '
0(
1#
#225
0#
#230
0-
1,
0+
1*
b110 !
b110 &
0)
b1001 "
b1001 '
1(
1#
#235
0#
#240
0*
b111 !
b111 &
1)
b1000 "
b1000 '
0(
1#
#245
0#
#250
12
01
10
0/
1.
1-
0,
1+
1*
b1000 !
b1000 &
0)
b111 "
b111 '
1(
1#
#255
0#
#260
0*
b1001 !
b1001 &
1)
b110 "
b110 '
0(
1#
#265
0#
#270
0-
1,
0+
1*
b1010 !
b1010 &
0)
b101 "
b101 '
1(
1#
#275
0#
#280
0*
b1011 !
b1011 &
1)
b100 "
b100 '
0(
1#
#285
0#
#290
00
1/
0.
1-
0,
1+
1*
b1100 !
b1100 &
0)
b11 "
b11 '
1(
1#
#295
0#
#300
0*
b1101 !
b1101 &
1)
b10 "
b10 '
0(
1#
#305
0#
#310
0-
1,
0+
1*
b1110 !
b1110 &
0)
b1 "
b1 '
1(
1#
#315
0#
#320
0*
b1111 !
b1111 &
1)
b0 "
b0 '
0(
1#
#325
0#
#330
02
11
10
0/
1.
1-
0,
1+
1*
b0 !
b0 &
0)
b1111 "
b1111 '
1(
1#
